README.txt
setup.py
Products/__init__.py
Products.sqlpfgadapter.egg-info/PKG-INFO
Products.sqlpfgadapter.egg-info/SOURCES.txt
Products.sqlpfgadapter.egg-info/dependency_links.txt
Products.sqlpfgadapter.egg-info/entry_points.txt
Products.sqlpfgadapter.egg-info/namespace_packages.txt
Products.sqlpfgadapter.egg-info/not-zip-safe
Products.sqlpfgadapter.egg-info/paster_plugins.txt
Products.sqlpfgadapter.egg-info/requires.txt
Products.sqlpfgadapter.egg-info/top_level.txt
Products/sqlpfgadapter/__init__.py
Products/sqlpfgadapter/config.py
Products/sqlpfgadapter/configure.zcml
Products/sqlpfgadapter/controlpanel.py
Products/sqlpfgadapter/database.py
Products/sqlpfgadapter/events.py
Products/sqlpfgadapter/interfaces.py
Products/sqlpfgadapter/profiles.zcml
Products/sqlpfgadapter/tests.py
Products/sqlpfgadapter/browser/__init__.py
Products/sqlpfgadapter/browser/configure.zcml
Products/sqlpfgadapter/content/__init__.py
Products/sqlpfgadapter/content/sqlAdapter.py
Products/sqlpfgadapter/profiles/default/controlpanel.xml
Products/sqlpfgadapter/profiles/default/metadata.xml
Products/sqlpfgadapter/profiles/default/registry.xml
Products/sqlpfgadapter/profiles/default/skins.xml
Products/sqlpfgadapter/profiles/default/types.xml
Products/sqlpfgadapter/profiles/default/workflows.xml
Products/sqlpfgadapter/profiles/default/types/FormFolder.xml
Products/sqlpfgadapter/profiles/default/types/SQLPFGAdapter.xml
Products/sqlpfgadapter/skins/sqlpfgadapter_images/action.gif
Products/sqlpfgadapter/skins/sqlpfgadapter_images/mysql.gif
Products/sqlpfgadapter/skins/sqlpfgadapter_images/sql-action.gif
Products/sqlpfgadapter/skins/sqlpfgadapter_images/sql.gif
docs/HISTORY.txt
docs/INSTALL.txt
docs/LICENSE.GPL
docs/LICENSE.txt
docs/TODO.txt