Metadata-Version: 1.0
Name: Products.sqlpfgadapter
Version: 0.1b2
Summary: A PloneFormGen Action Adapter for SQL storage
Home-page: http://plone.org/products/sqlpfgadapter
Author: Kees Hink
Author-email: hink@gw20e.com
License: GPL
Keywords: web plone sql
Platform: UNKNOWN
Classifier: Framework :: Plone
Classifier: Programming Language :: Python
